ipyregulus/__init__.py
ipyregulus/_version.py
ipyregulus/axesctrl.py
ipyregulus/base.py
ipyregulus/basetreeview.py
ipyregulus/controls.py
ipyregulus/data_widget.py
ipyregulus/details_view.py
ipyregulus/graph_view.py
ipyregulus/projection_view.py
ipyregulus/projection_widget.py
ipyregulus/tree_view.py
ipyregulus/treeview.py
ipyregulus/core/__init__.py
ipyregulus/core/axis.py
ipyregulus/core/base.py
ipyregulus/core/trait_types.py
ipyregulus/filters/__init__.py
ipyregulus/filters/basic_filters.py
ipyregulus/filters/filters.py
ipyregulus/filters/trigger.py
ipyregulus/tree/__init__.py
ipyregulus/tree/serializer.py
ipyregulus/tree/tree_widget.py
ipyregulus/utils/__init__.py
ipyregulus/utils/projection.py
ipyregulus-0.8.5.dist-info/LICENSE
ipyregulus-0.8.5.dist-info/METADATA
ipyregulus-0.8.5.dist-info/WHEEL
ipyregulus-0.8.5.dist-info/top_level.txt
ipyregulus-0.8.5.dist-info/RECORD
