Metadata-Version: 2.1
Name: ipyregulus
Version: 0.8.5
Summary: Regulus extension for Jupyter
Home-page: https://github.com/yarden-livnat/ipyregulus
Author: Yarden Livnat
Author-email: yarden@sci.utah.edu
License: BSD
Keywords: Interactive,JupyterLab
Platform: Linux
Platform: Mac OS X
Platform: Windows
Classifier: Intended Audience :: Developers
Classifier: Intended Audience :: Science/Research
Classifier: License :: OSI Approved :: BSD License
Classifier: Programming Language :: Python :: 3.7
Classifier: Framework :: Jupyter
Requires-Dist: ipywidgets (>=7.5.0)
Requires-Dist: ipydatawidgets
Requires-Dist: traitlets (>4.3.0)
Requires-Dist: traittypes
Requires-Dist: pandas
Requires-Dist: regulus (>=0.8.0)
